Metadata-Version: 2.1
Name: mibanco_auto_web
Version: 1.0.5
Summary: A simple functional test library using Python and Selenium
Author: Automation & Performance Team
Keywords: selenium,testing,web,chrome,firefox,edge,python,cucumber
Classifier: Development Status :: 3 - Alpha
Classifier: Intended Audience :: Developers
Classifier: License :: OSI Approved :: MIT License
Classifier: Programming Language :: Python :: 3.12
License-File: LICENSE
Requires-Dist: behave==1.2.6
Requires-Dist: behave2cucumber==1.0.3
Requires-Dist: docxcompose==1.4.0
Requires-Dist: docxtpl==0.16.8
Requires-Dist: psutil==5.9.8
Requires-Dist: pillow==10.3.0
Requires-Dist: openpyxl==3.1.2
Requires-Dist: customtkinter==5.2.2
Requires-Dist: PyPDF2==3.0.1
Requires-Dist: python-docx==1.1.0
Requires-Dist: selenium==4.20.0
